reportify/__init__.py
reportify/report.py
reportify/send_discord.py
reportify/controller/__init__.py
reportify/controller/report_controller.py
reportify/model/__init__.py
reportify/model/dashboard/__init__.py
reportify/model/dashboard/dashboard_abstract.py
reportify/model/dashboard/dashboard_developer.py
reportify/model/dashboard/dashboard_organization.py
reportify/model/dashboard/dashboard_repository.py
reportify/model/dashboard/dashboard_team.py
reportify/model/dashboard/dashboard_team_graph.py
reportify/model/exceptions/__init__.py
reportify/model/exceptions/exit_blank_choice_exception.py
reportify/model/exceptions/team_members_exception.py
reportify/view/__init__.py
reportify/view/dashboard_view.py
reportify/view/generate_all.py
reportify_ifes-1.3.0.dist-info/licenses/LICENSE
reportify_ifes-1.3.0.dist-info/METADATA
reportify_ifes-1.3.0.dist-info/WHEEL
reportify_ifes-1.3.0.dist-info/top_level.txt
reportify_ifes-1.3.0.dist-info/RECORD
